{
    "Título": "Academia Brasileira de Letras",
    "Academia Brasileira de Letras": [],
    "Lema": [
        "Lema",
        "\"Ad immortalitatem(Rumo à imortalidade)\""
    ],
    "Tipo": [
        "Tipo",
        "Associação literária"
    ],
    "Fundação": [
        "Fundação",
        "20 de julhode1897(127 anos)[1]"
    ],
    "Sede": [
        "Sede",
        "Rio de Janeiro, Brasil"
    ],
    "Membros": [
        "Membros",
        "Cf.Index Academicorum"
    ],
    "Línguas oficiais": [
        "Línguas oficiais",
        "Português"
    ],
    "Presidente": [
        "Presidente",
        "Merval Pereira"
    ],
    "Sítio oficial": [
        "Sítio oficial",
        "www.academia.org.br"
    ]
}