{
    "Título": "Alto Lomami",
    "Alto Lomami": [],
    "Província": [],
    "Localização": [],
    "País": [
        "País",
        "República Democrática do Congo"
    ],
    "Administração": [],
    "Capital": [
        "Capital",
        "Camina"
    ],
    "Características geográficas": [],
    "Área total[1]": [
        "Área total[1]",
        "108 204 km²"
    ],
    "População total(12/2005 estimativa)[1]": [
        "População total(12/2005 estimativa)[1]",
        "2 540 127 hab."
    ],
    "Densidade": [
        "Densidade",
        "23,5 hab./km²"
    ]
}