{
    "Título": "Büyükçekmece",
    "Büyükçekmece": [],
    "Distrito(ilçe)": [],
    "Localização": [],
    "País": [
        "País",
        "Turquia"
    ],
    "Região": [
        "Região",
        "Mármara"
    ],
    "Província": [
        "Província",
        "Istambul"
    ],
    "Características geográficas": [],
    "Área total": [
        "Área total",
        "196 km²"
    ],
    "População total(2008)": [
        "População total(2008)",
        "163 140 hab."
    ],
    "Densidade": [
        "Densidade",
        "832,3 hab./km²"
    ]
}