{
    "Título": "Cuango",
    "Cuango": [],
    "Província": [],
    "Localização": [],
    "País": [
        "País",
        "República Democrática do Congo"
    ],
    "Administração": [],
    "Capital": [
        "Capital",
        "Kenge"
    ],
    "Características geográficas": [],
    "Área total[1]": [
        "Área total[1]",
        "89 974 km²"
    ],
    "População total(12/2005 estimativa)[1]": [
        "População total(12/2005 estimativa)[1]",
        "1 994 036 hab."
    ],
    "Densidade": [
        "Densidade",
        "22,2 hab./km²"
    ]
}