{
    "Título": "Departamento do Tesouro dos Estados Unidos",
    "Departamento do Tesouro dos Estados Unidos": [],
    "United States Department of the Treasury": [],
    "Resumo doDepartamento": [],
    "Formação": [
        "Formação",
        "2 de setembro de 1789(1789-09-02)"
    ],
    "Tipo": [
        "Tipo",
        "Departamento"
    ],
    "Jurisdição": [
        "Jurisdição",
        "Governo Federal dos Estados Unidos"
    ],
    "Sede": [
        "Sede",
        "Avenida Pensilvânia1500,NWWashington, D.C., Estados Unidos"
    ],
    "Empregados": [
        "Empregados",
        "87,336 (2019)"
    ],
    "Orçamento anual": [
        "Orçamento anual",
        "US$20,2 bilhões(2024)[1]"
    ],
    "Executivos da agência": [
        "Executivos da agência",
        "Scott Bessent,(Secretário do Tesouro)"
    ],
    "Agências filhas": [
        "Agências filhas",
        "Internal Revenue ServiceCasa da MoedaOutras diversas"
    ],
    "Sítio oficial": [
        "Sítio oficial",
        "treasury.gov"
    ]
}