{
    "Título": "Eyüp",
    "Eyüp": [],
    "Distrito(ilçe)": [],
    "Localização": [],
    "País": [
        "País",
        "Turquia"
    ],
    "Região": [
        "Região",
        "Mármara"
    ],
    "Província": [
        "Província",
        "Istambul"
    ],
    "Características geográficas": [],
    "Área total": [
        "Área total",
        "242 km²"
    ],
    "População total(2008)": [
        "População total(2008)",
        "323 038 hab."
    ],
    "Densidade": [
        "Densidade",
        "1 334,9 hab./km²"
    ]
}