{
    "Título": "GaziantepeGaziantep • Antioquia no Tauro • Dolique • Teluche • Ayintap • Antep • Dîlok",
    "GaziantepeGaziantep • Antioquia no Tauro • Dolique • Teluche • Ayintap • Antep • Dîlok": [],
    "Capital deárea metropolitana(büyükşehir)": [],
    "Localização": [],
    "Coordenadas": [
        "Coordenadas",
        "37° 03′ 46″ N, 37° 22′ 45″ L"
    ],
    "País": [
        "País",
        "Turquia"
    ],
    "Região": [
        "Região",
        "Sudeste da Anatólia"
    ],
    "Província": [
        "Província",
        "Gaziantepe"
    ],
    "Características geográficas": [],
    "Área total[1]": [
        "Área total[1]",
        "2 939 km²"
    ],
    "População total(dezembro de 2021)[2]": [
        "População total(dezembro de 2021)[2]",
        "1 808 948 hab."
    ],
    "Densidade": [
        "Densidade",
        "615,5 hab./km²"
    ],
    "Altitude": [
        "Altitude",
        "860 m"
    ],
    "Código postal": [
        "Código postal",
        "27000"
    ],
    "Prefixo telefónico": [
        "Prefixo telefónico",
        "342"
    ],
    "Sítio": [
        "Sítio",
        "www.gaziantep.bel.tr"
    ]
}