{
    "Título": "Hong Kong香港",
    "Hong Kong香港": [],
    "Região administrativa especial": [
        "Região administrativa especial",
        "Hong Kong"
    ],
    "Região Administrativa Especial de Hong Kong da República Popular da China": [],
    "Gentílico": [
        "Gentílico",
        "hong-konguês, honconguês[1]"
    ],
    "Localização": [],
    "Coordenadas": [
        "Coordenadas",
        "22° 18′ 00″ N, 114° 12′ 00″ L"
    ],
    "País": [
        "País",
        "China"
    ],
    "História": [],
    "Incorporação àDinastia Chin": [
        "Incorporação àDinastia Chin",
        "214 a.C."
    ],
    "Ocupação britânica": [
        "Ocupação britânica",
        "25 de janeiro de 1841"
    ],
    "Tratado de Nanquim": [
        "Tratado de Nanquim",
        "29 de agosto de 1842"
    ],
    "Ocupação japonesa": [
        "Ocupação japonesa",
        "25 de dezembro de 1941 – 15 de agosto de 1945"
    ],
    "Declaração sino-britânica": [
        "Declaração sino-britânica",
        "19 de dezembro de 1984"
    ],
    "Devolução para a China": [
        "Devolução para a China",
        "30 de junho de 1997"
    ],
    "Administração": [],
    "Chefe do Executivo": [
        "Chefe do Executivo",
        "John Lee Ka-chiu"
    ],
    "Características geográficas": [],
    "Área total": [
        "Área total",
        "1 104 km²"
    ],
    "População total": [
        "População total",
        "7 184 000[2]hab."
    ],
    "Indicadores": [],
    "IDH(2021)[3]": [
        "IDH(2021)[3]",
        "0,952—muito alto"
    ],
    "Outras informações": [],
    "Gini(2009)": [
        "Gini(2009)",
        "43,4[4]"
    ],
    "PIB(2013, basePPC)": [
        "PIB(2013, basePPC)",
        "381,663bilhões*[5]"
    ],
    "PIB per capita": [
        "PIB per capita",
        "38 605[5]"
    ],
    "PIB(nominal)": [
        "PIB(nominal)",
        "279,654bilhões*[5]"
    ],
    "Moeda": [
        "Moeda",
        "Dólar de Hong Kong"
    ],
    "Sítio": [
        "Sítio",
        "www.gov.hk"
    ]
}