{
    "Título": "Mesquita YeniMesquita Nova, Mesquita Yeni Valide",
    "Mesquita YeniMesquita Nova, Mesquita Yeni Valide": [],
    "Informações gerais": [],
    "Estilodominante": [
        "Estilodominante",
        "otomano"
    ],
    "Arquiteto": [
        "Arquiteto",
        "Davut Aga, Dalgic Ahmed Cavus, Mustafa Aga"
    ],
    "Início da construção": [
        "Início da construção",
        "1561"
    ],
    "Fim da construção": [
        "Fim da construção",
        "1665"
    ],
    "Religião": [
        "Religião",
        "muçulmana"
    ],
    "Geografia": [],
    "País": [
        "País",
        "Turquia"
    ],
    "Localização": [
        "Localização",
        "Eminönü,Fatih"
    ],
    "Região": [
        "Região",
        "Istambul"
    ],
    "Coordenadas": [
        "Coordenadas",
        "41° 01′ 01″ N, 28° 58′ 20″ L"
    ],
    "": []
}