{
    "Título": "Mesquita de Sokollu Mehmet Paşa",
    "Mesquita de Sokollu Mehmet Paşa": [],
    "Informações gerais": [],
    "Estilodominante": [
        "Estilodominante",
        "otomano"
    ],
    "Arquiteto": [
        "Arquiteto",
        "Mimar Sinan"
    ],
    "Início da construção": [
        "Início da construção",
        "1571"
    ],
    "Fim da construção": [
        "Fim da construção",
        "1572"
    ],
    "Religião": [
        "Religião",
        "muçulmana"
    ],
    "Geografia": [],
    "País": [
        "País",
        "Turquia"
    ],
    "Localização": [
        "Localização",
        "Fatih,Eminönü,Kadırga"
    ],
    "Região": [
        "Região",
        "Istambul"
    ],
    "Coordenadas": [
        "Coordenadas",
        "41° 00′ 17″ N, 28° 58′ 19″ L"
    ],
    "": []
}