{
    "Título": "República do Níger",
    "República do Níger": [],
    "République du Niger": [],
    "Lema:Fraternité, Travail, Progrès(Francês)(\"Fraternidade, Trabalho, Progresso\")": [],
    "Hino:La Nigérienne": [],
    "Capitale maior cidade": [
        "Capitale maior cidade",
        "Niamei"
    ],
    "Língua oficial": [
        "Língua oficial",
        "Francês(oficial)[1]Línguas nacionais:[2]Árabe,buduma,fula,gur,hauçá,songai,canúri,zarma,tamaxeque,tassauaqueetubu"
    ],
    "Gentílico": [
        "Gentílico",
        "nigerino(a)[3][4][5];nigerense[3]"
    ],
    "Governo": [
        "Governo",
        "Repúblicasemipresidencialistaunitáriasob umajunta militar"
    ],
    "•Presidente do Conselho Nacional de Salvaguarda da Pátria": [
        "•Presidente do Conselho Nacional de Salvaguarda da Pátria",
        "Abdourahamane Tchiani"
    ],
    "•Primeiro-ministro": [
        "•Primeiro-ministro",
        "Ali Lamine Zeine"
    ],
    "IndependênciadaFrança": [],
    "• Data": [
        "• Data",
        "3 de agostode1960"
    ],
    "Área": [],
    "• Total": [
        "• Total",
        "US$14,6bilhões*[7]"
    ],
    "Fronteira": [
        "Fronteira",
        "Argélia,Líbia,Chade,Nigéria,Benim,Burquina FassoeMali"
    ],
    "População": [],
    "• Estimativa para 2023": [
        "• Estimativa para 2023",
        "25 396 840[6]hab."
    ],
    "•Densidade": [
        "•Densidade",
        "13,5 hab./km² (60.º)"
    ],
    "PIB(basePPC)": [
        "PIB(basePPC)",
        "Estimativa para 2022"
    ],
    "•Per capita": [
        "•Per capita",
        "US$ 484[7]"
    ],
    "IDH(2021)": [
        "IDH(2021)",
        "0,400 (189.º) –muito baixo[8]"
    ],
    "Moeda": [
        "Moeda",
        "Franco CFA(XOF)"
    ],
    "Fuso horário": [
        "Fuso horário",
        "UTC(UTC+1)"
    ],
    "• Verão (DST)": [
        "• Verão (DST)",
        "(UTC+2)"
    ],
    "Cód. Internet": [
        "Cód. Internet",
        ".ne"
    ],
    "Cód. telef.": [
        "Cód. telef.",
        "+227"
    ]
}