{
    "Título": "Shimonoseki下関市",
    "Shimonoseki下関市": [],
    "Localização": [],
    "País": [
        "País",
        "Japão"
    ],
    "Prefeitura": [
        "Prefeitura",
        "Yamaguchi"
    ],
    "Características geográficas": [],
    "Área total": [
        "Área total",
        "716,14 km²"
    ],
    "População total(1 de outubrode2010)": [
        "População total(1 de outubrode2010)",
        "280 386 hab."
    ],
    "Sítio": [
        "Sítio",
        "http://www.city.shimonoseki.yamaguchi.jp/"
    ]
}