{
    "Título": "Sublime Estado Otomanoدولت عليه عثمانیهDevlet-i ʿAlīye-i ʿOsmānīye",
    "Sublime Estado Otomanoدولت عليه عثمانیهDevlet-i ʿAlīye-i ʿOsmānīye": [],
    "←c.1299—1922→": [
        "←",
        "c.1299—1922",
        "→"
    ],
    "Bandeira(1844–1922)Brasão(1882–1922)Bandeira(1844–1922)Brasão(1882–1922)": [
        "Bandeira(1844–1922)",
        "",
        "Brasão(1882–1922)",
        "Bandeira(1844–1922)",
        "",
        "Brasão(1882–1922)"
    ],
    "Lema nacional": [
        "Lema nacional",
        "دولت ابد مدتDevlet-i Ebed-müddet\"O Estado Eterno\"[1]"
    ],
    "Hino nacional": [
        "Hino nacional",
        "Vários\"Mahmudiye Marşı\"(1829–1839, 1918–1922)\"Mecidiye Marşı\"(1839–1861)\"Aziziye Marşı\"(1861–1876)\"Hamidiye Marşı\"(Modificado)(1876–1909)\"Reşadiye Marşı\"(1909–1918)"
    ],
    "": [],
    "Língua oficial": [
        "Língua oficial",
        "turco otomano"
    ],
    "Religião oficial": [
        "Religião oficial",
        "islamismosunita"
    ],
    "Moeda": [
        "Moeda",
        "akçesultaniparakuruş(piastra)lira"
    ],
    "Forma de governo": [
        "Forma de governo",
        "monarquia absoluta(c. 1299–1876; 1878–1908; 1920–1922)monarquia constitucionalparlamentarunitária(1876–1878; 1908–1920)Triunvirato ditatorial(1913–1918)"
    ],
    "Sultão": [],
    "Califa": [],
    "Grão-vizir": [],
    "Assembleia Geral(1876–1878; 1908–1920)": [],
    "História": [
        "História",
        ""
    ]
}