{
    "Título": "Tóquio東京都",
    "Tóquio東京都": [],
    "Capital doJapão": [],
    "Metrópole de Tóquio": [],
    "Gentílico": [
        "Gentílico",
        "toquiota[1]"
    ],
    "Localização": [],
    "Coordenadas": [
        "Coordenadas",
        "35° 41′ 00″ N, 139° 46′ 00″ L"
    ],
    "País": [
        "País",
        "Japão"
    ],
    "Prefeitura": [
        "Prefeitura",
        "Tóquio"
    ],
    "História": [],
    "Fundação": [
        "Fundação",
        "1457"
    ],
    "Administração": [],
    "Governador(a)": [
        "Governador(a)",
        "Yuriko Koike"
    ],
    "Características geográficas": [],
    "Área total": [
        "Área total",
        "2 189,08"
    ],
    "População total": [
        "População total",
        "13 503 810[2]hab."
    ],
    "• Populaçãometropolitana": [
        "• Populaçãometropolitana",
        "38,140,000"
    ],
    "Densidade": [
        "Densidade",
        "6 354 hab./km²"
    ],
    "Fuso horário": [
        "Fuso horário",
        "Japão padrão(UTC+9)"
    ],
    "Sítio": [
        "Sítio",
        "www.metro.tokyo.jp"
    ]
}