{
    "Título": "Universo Online",
    "Universo Online": [],
    "Universo Online S/A": [],
    "Slogan": [
        "Slogan",
        "Seu universo online"
    ],
    "Proprietário(s)": [
        "Proprietário(s)",
        "OFL S.A. (controlador)"
    ],
    "Requer pagamento?": [
        "Requer pagamento?",
        "Para certos conteúdos, sim"
    ],
    "Gênero": [
        "Gênero",
        "Portal"
    ],
    "Cadastro": [
        "Cadastro",
        "Público / Pago / Não necessita cadastro"
    ],
    "País de origem": [
        "País de origem",
        "Brasil"
    ],
    "Idioma(s)": [
        "Idioma(s)",
        "português"
    ],
    "Lançamento": [
        "Lançamento",
        "28 de abrilde1996(28 anos)"
    ],
    "Endereço eletrônico": [
        "Endereço eletrônico",
        "uol.com.br"
    ]
}