{
    "Título": "Universidade Carnegie MellonCarnegie Mellon University",
    "Universidade Carnegie MellonCarnegie Mellon University": [],
    "Tipo": [
        "Tipo",
        "universidade privada, universidade de investigação, instituição educativa privada sem fins lucrativos"
    ],
    "Inauguração": [
        "Inauguração",
        "1900(125 anos)"
    ],
    "Administração": [],
    "Presidente(a)": [
        "Presidente(a)",
        "Farnam Jahanian"
    ],
    "Geografia": [],
    "Coordenadas": [
        "Coordenadas",
        "40° 26' 33\" N79° 56' 36\" O"
    ],
    "Localização": [
        "Localização",
        "Pittsburgh- Estados Unidos"
    ]
}