{
    "Título": "Veneza e sua Lagoa★Património MundialdaUNESCO",
    "Veneza e sua Lagoa★Património MundialdaUNESCO": [],
    "Critérios": [
        "Critérios",
        "i, ii, iii, iv, v, vi"
    ],
    "Referência": [
        "Referência",
        "394"
    ],
    "Região♦": [
        "Região♦",
        "Europa"
    ],
    "País": [
        "País",
        "Itália"
    ],
    "Coordenadas": [
        "Coordenadas",
        "45° 26' N 12° 19' E"
    ],
    "Histórico de inscrição": [],
    "Inscrição": [
        "Inscrição",
        "1987"
    ]
}