{
    "Título": "VersalhesVersailles",
    "VersalhesVersailles": [],
    "Comuna francesa": [],
    "Gentílico": [
        "Gentílico",
        "Versalhês"
    ],
    "Localização": [],
    "Coordenadas": [
        "Coordenadas",
        "48° 48′ 19″ N, 2° 08′ 06″ L"
    ],
    "País": [
        "País",
        "França"
    ],
    "Região": [
        "Região",
        "Ilha de França"
    ],
    "Departamento": [
        "Departamento",
        "Yvelines"
    ],
    "Administração": [],
    "Prefeito": [
        "Prefeito",
        "François de Mazières"
    ],
    "Características geográficas": [],
    "Área total": [
        "Área total",
        "26,18 km²"
    ],
    "População total(2018)[1]": [
        "População total(2018)[1]",
        "87 253 hab."
    ],
    "Densidade": [
        "Densidade",
        "3 332,8 hab./km²"
    ],
    "Altitude máxima": [
        "Altitude máxima",
        "103 m"
    ],
    "Altitude mínima": [
        "Altitude mínima",
        "103 m"
    ],
    "Código Postal": [
        "Código Postal",
        "78000"
    ],
    "Código INSEE": [
        "Código INSEE",
        "78646"
    ],
    "Sítio": [
        "Sítio",
        "Versailles.fr"
    ]
}