{
    "Título": "Ziyad al-Nakhalahزياد النخالة",
    "Ziyad al-Nakhalahزياد النخالة": [],
    "Secretário-Geral doMovimento da Jihad Islâmica na Palestina": [],
    "Período": [
        "Período",
        "28 de setembro de 2018 — atualidade"
    ],
    "Antecessor(a)": [
        "Antecessor(a)",
        "Ramadan Shalah"
    ],
    "Dados pessoais": [],
    "Nascimento": [
        "Nascimento",
        "1953(72 anos)Khan Yunis,Protetorado de Toda-Palestina"
    ],
    "Nacionalidade": [
        "Nacionalidade",
        "Palestiniano"
    ],
    "Partido": [
        "Partido",
        "Movimento da Jihad Islâmica na Palestina"
    ]
}